kiboko_shortcodes/__init__.py
kiboko_shortcodes/kiboko_shortcodes.py
kiboko_shortcodes-0.2.dist-info/METADATA
kiboko_shortcodes-0.2.dist-info/WHEEL
kiboko_shortcodes-0.2.dist-info/top_level.txt
kiboko_shortcodes-0.2.dist-info/RECORD
